setup.py
src/libthryft.egg-info/PKG-INFO
src/libthryft.egg-info/SOURCES.txt
src/libthryft.egg-info/dependency_links.txt
src/libthryft.egg-info/top_level.txt
src/thryft/__init__.py
src/thryft/protocol/__init__.py
src/thryft/protocol/_abstract_input_protocol.py
src/thryft/protocol/_abstract_output_protocol.py
src/thryft/protocol/_input_protocol.py
src/thryft/protocol/_output_protocol.py
src/thryft/protocol/_stacked_input_protocol.py
src/thryft/protocol/_stacked_output_protocol.py
src/thryft/protocol/builtins_input_protocol.py
src/thryft/protocol/builtins_output_protocol.py
src/thryft/protocol/json_input_protocol.py
src/thryft/protocol/json_output_protocol.py
src/thryft/protocol/string_map_output_protocol.py
src/thryft/protocol/type.py